is_computer_on/__init__.py
is_computer_on-1.0.1.dist-info/METADATA
is_computer_on-1.0.1.dist-info/WHEEL
is_computer_on-1.0.1.dist-info/top_level.txt
is_computer_on-1.0.1.dist-info/RECORD
