Metadata-Version: 2.1
Name: is-computer-on
Version: 1.0.1
Summary: A python package to empirically determine if the processing unit is functional.
Home-page: https://github.com/GrantGMiller/is_computer_on
Author: Grant miller
Author-email: grant@grant-miller.com
License: PSF
Project-URL: Source Code, https://github.com/GrantGMiller/is_computer_on
Keywords: is computer on
Platform: UNKNOWN
